Workbook

Sheet Input -->
B17: Input -->

Sheet Drivers
B1: Drivers
B3: Selected case | C3: ='Discounted Cash Flows'!C3 -> 2
B5: Inflation
B6: Expected long-term inflation Italy | C6: 0.01
B7: Expected long-term inflation Vietnam | C7: 0.03
B9: Price of production
B10: Price of production in Italy | C10: 15500
B11: Price of production in Vietnam | C11: 11000
B13: Estimated initial investment (in EUR)
B14: Best case | C14: 320000000
B15: Base case | C15: 350000000
B16: Worst case | C16: 380000000
B18: Useful life (years) | C18: 10
B20: WC Italy
B21: DIO | C21: 25
B22: DPO | C22: 30
B23: Net Trading Cycle (days) | C23: =C21-C22 -> -5
B25: Company beta | C25: 0.9
B27: Financing facilities
B28: Senior Facility (million EUR) | C28: 200000000
B29: Interest rate Senior Facility | C29: 0.05
B30: Repay Senior Facility in | C30: 10 years
B33: Covenant 1
B34: Production should not be less than 15,000 per year.
B35: Otherwise penalty of $1,000,000 per year.
B37: Tax rate | C37: 0.3
B39: Residual value of the project | C39: 100000000
B41: Comparable companies | C41: Leverage (D/E) | D41: Beta
B42: Company A | C42: 0.8 | D42: 0.6
B43: Company B | C43: 0.9 | D43: 0.65
B44: Company C | C44: 0.85 | D44: 0.57
B46: Market risk premium in Vietnam | C46: 0.06
B47: Market risk premium in Italy | C47: 0.05
B49: Risk-free rate in Vietnam | C49: 0.03
B50: Risk-free rate in Italy | C50: 0.02

Sheet Workings -->
B17: Workings -->

Sheet Savings forecast
B1: Savings forecast
B3: Best volume | C3: 22000
B4: Base volume | C4: 20000
B5: Worst volume | C5: 18000
B7: Volume (in units) | C7: 1 | D7: 2 | E7: 3 | F7: 4 | G7: 5 | H7: 6 | I7: 7 | J7: 8 | K7: 9 | L7: 10
B8: Best case | C8: =$C3*C14 -> 18700 | D8: =$C3*D14 -> 19140 | E8: =$C3*E14 -> 19580 | F8: =$C3*F14 -> 20240 | G8: =$C3*G14 -> 19800 | H8: =$C3*H14 -> 19580 | I8: =$C3*I14 -> 19140 | J8: =$C3*J14 -> 18700 | ... L8: =$C3*L14 -> 18260
B9: Base case | C9: =$C4*C15 -> 16000 | D9: =$C4*D15 -> 17000 | E9: =$C4*E15 -> 17400 | F9: =$C4*F15 -> 18000 | G9: =$C4*G15 -> 17600 | H9: =$C4*H15 -> 17400 | I9: =$C4*I15 -> 17000 | J9: =$C4*J15 -> 16600 | ... L9: =$C4*L15 -> 16200
B10: Worst case | C10: =$C5*C16 -> 13500 | D10: =$C5*D16 -> 14400 | E10: =$C5*E16 -> 14760 | F10: =$C5*F16 -> 15120 | G10: =$C5*G16 -> 14940 | H10: =$C5*H16 -> 14760 | I10: =$C5*I16 -> 14400 | J10: =$C5*J16 -> 14040 | ... L10: =$C5*L16 -> 13680
B11: Selected case | C11: =CHOOSE(Drivers!$C$3,'Savings forecast'!C8,'Savings forecast'!C9,'Savings forecast'!C10) -> 16000 | D11: =CHOOSE(Drivers!$C$3,'Savings forecast'!D8,'Savings forecast'!D9,'Savings forecast'!D10) -> 17000 | E11: =CHOOSE(Drivers!$C$3,'Savings forecast'!E8,'Savings forecast'!E9,'Savings forecast'!E10) -> 17400 | F11: =CHOOSE(Drivers!$C$3,'Savings forecast'!F8,'Savings forecast'!F9,'Savings forecast'!F10) -> 18000 | G11: =CHOOSE(Drivers!$C$3,'Savings forecast'!G8,'Savings forecast'!G9,'Savings forecast'!G10) -> 17600 | H11: =CHOOSE(Drivers!$C$3,'Savings forecast'!H8,'Savings forecast'!H9,'Savings forecast'!H10) -> 17400 | I11: =CHOOSE(Drivers!$C$3,'Savings forecast'!I8,'Savings forecast'!I9,'Savings forecast'!I10) -> 17000 | J11: =CHOOSE(Drivers!$C$3,'Savings forecast'!J8,'Savings forecast'!J9,'Savings forecast'!J10) -> 16600 | ... L11: =CHOOSE(Drivers!$C$3,'Savings forecast'!L8,'Savings forecast'!L9,'Savings forecast'!L10) -> 16200
B13: Productivity (as a %) | C13: 1 | D13: 2 | E13: 3 | F13: 4 | G13: 5 | H13: 6 | I13: 7 | J13: 8 | K13: 9 | L13: 10
B14: Best case | C14: 0.85 | D14: 0.87 | E14: 0.89 | F14: 0.92 | G14: 0.9 | H14: 0.89 | I14: 0.87 | J14: 0.85 | K14: 0.84 | L14: 0.83
B15: Base case | C15: 0.8 | D15: 0.85 | E15: 0.87 | F15: 0.9 | G15: 0.88 | H15: 0.87 | I15: 0.85 | J15: 0.83 | K15: 0.82 | L15: 0.81
B16: Worst case | C16: 0.75 | D16: 0.8 | E16: 0.82 | F16: 0.84 | G16: 0.83 | H16: 0.82 | I16: 0.8 | J16: 0.78 | K16: 0.77 | L16: 0.76
B19: Expected long-term inflation Italy | C19: =Drivers!C6 -> 0.01
B20: Expected long-term inflation Vietnam | C20: =Drivers!C7 -> 0.03
B22: Price of production (EUR) | C22: 1 | D22: 2 | E22: 3 | F22: 4 | G22: 5 | H22: 6 | I22: 7 | J22: 8 | K22: 9 | L22: 10
B23: Price of production in Italy | C23: =Drivers!C10 -> 15500 | D23: =C23*(1+$C19) -> 15655 | E23: =D23*(1+$C19) -> 15811.55 | F23: =E23*(1+$C19) -> 15969.665 | G23: =F23*(1+$C19) -> 16129.362 | H23: =G23*(1+$C19) -> 16290.656 | I23: =H23*(1+$C19) -> 16453.562 | J23: =I23*(1+$C19) -> 16618.098 | K23: =J23*(1+$C19) -> 16784.279 | L23: =K23*(1+$C19) -> 16952.122
B24: Price of production in Vietnam | C24: =Drivers!C11 -> 11000 | D24: =C24*(1+$C20) -> 11330 | E24: =D24*(1+$C20) -> 11669.9 | F24: =E24*(1+$C20) -> 12019.997 | G24: =F24*(1+$C20) -> 12380.597 | H24: =G24*(1+$C20) -> 12752.015 | I24: =H24*(1+$C20) -> 13134.575 | J24: =I24*(1+$C20) -> 13528.613 | K24: =J24*(1+$C20) -> 13934.471 | L24: =K24*(1+$C20) -> 14352.505
B25: Savings per unit | C25: =C23-C24 -> 4500 | D25: =D23-D24 -> 4325 | E25: =E23-E24 -> 4141.65 | F25: =F23-F24 -> 3949.6685 | G25: =G23-G24 -> 3748.7652 | H25: =H23-H24 -> 3538.641 | I25: =I23-I24 -> 3318.9871 | J25: =J23-J24 -> 3089.4854 | ... L25: =L23-L24 -> 2599.6167
B27: Total savings (EUR) | C27: 1 | D27: 2 | E27: 3 | F27: 4 | G27: 5 | H27: 6 | I27: 7 | J27: 8 | K27: 9 | L27: 10
B28: Best case | C28: =C8*C$25 -> 84150000 | D28: =D8*D$25 -> 82780500 | E28: =E8*E$25 -> 81093507 | F28: =F8*F$25 -> 79941290 | G28: =G8*G$25 -> 74225552 | H28: =H8*H$25 -> 69286590 | I28: =I8*I$25 -> 63525413 | J28: =J8*J$25 -> 57773378 | ... L28: =L8*L$25 -> 47469001
B29: Base case | C29: =C9*C$25 -> 72000000 | D29: =D9*D$25 -> 73525000 | E29: =E9*E$25 -> 72064710 | F29: =F9*F$25 -> 71094033 | G29: =G9*G$25 -> 65978268 | H29: =H9*H$25 -> 61572353 | I29: =I9*I$25 -> 56422780 | J29: =J9*J$25 -> 51285458 | ... L29: =L9*L$25 -> 42113791
B30: Worst case | C30: =C10*C$25 -> 60750000 | D30: =D10*D$25 -> 62280000 | E30: =E10*E$25 -> 61130754 | F30: =F10*F$25 -> 59718988 | G30: =G10*G$25 -> 56006553 | H30: =H10*H$25 -> 52230341 | I30: =I10*I$25 -> 47793414 | J30: =J10*J$25 -> 43376376 | ... L30: =L10*L$25 -> 35562757
B31: Selected case | C31: =CHOOSE(Drivers!$C$3,'Savings forecast'!C28,'Savings forecast'!C29,'Savings forecast'!C30) -> 72000000 | D31: =CHOOSE(Drivers!$C$3,'Savings forecast'!D28,'Savings forecast'!D29,'Savings forecast'!D30) -> 73525000 | E31: =CHOOSE(Drivers!$C$3,'Savings forecast'!E28,'Savings forecast'!E29,'Savings forecast'!E30) -> 72064710 | F31: =CHOOSE(Drivers!$C$3,'Savings forecast'!F28,'Savings forecast'!F29,'Savings forecast'!F30) -> 71094033 | G31: =CHOOSE(Drivers!$C$3,'Savings forecast'!G28,'Savings forecast'!G29,'Savings forecast'!G30) -> 65978268 | H31: =CHOOSE(Drivers!$C$3,'Savings forecast'!H28,'Savings forecast'!H29,'Savings forecast'!H30) -> 61572353 | I31: =CHOOSE(Drivers!$C$3,'Savings forecast'!I28,'Savings forecast'!I29,'Savings forecast'!I30) -> 56422780 | J31: =CHOOSE(Drivers!$C$3,'Savings forecast'!J28,'Savings forecast'!J29,'Savings forecast'!J30) -> 51285458 | ... L31: =CHOOSE(Drivers!$C$3,'Savings forecast'!L28,'Savings forecast'!L29,'Savings forecast'!L30) -> 42113791

Sheet Fixed asset roll-forward
B1: Fixed asset roll-forward
B3: Estimated initial investment (in EUR)
B4: Best case | C4: =Drivers!C14 -> 320000000
B5: Base case | C5: =Drivers!C15 -> 350000000
B6: Worst case | C6: =Drivers!C16 -> 380000000
B8: =Drivers!B18 -> Useful life (years) | C8: 10
B10: Investment plan | C10: 0 | D10: 1 | E10: 2 | F10: 3 | G10: 4 | H10: 5 | I10: 6 | J10: 7 | K10: 8 | L10: 9 | M10: 10
B11: Year 1 | C11: 0.8 | D11: 0.1 | E11: 0.1 | F11: 0.03 | G11: 0.03 | H11: 0.03 | I11: 0.03 | J11: 0.03 | K11: 0.03 | L11: 0.03 | M11: 0.03
B13: in EUR | C13: 1 | D13: 2 | E13: 3 | F13: 4 | G13: 5 | H13: 6 | I13: 7 | J13: 8 | K13: 9 | L13: 10
B14: Beginning PP&E | C14: =CHOOSE(Drivers!$C$3,'Fixed asset roll-forward'!$C4,'Fixed asset roll-forward'!$C5,'Fixed asset roll-forward'!$C6)*'Fixed asset roll-forward'!C11 -> 280000000 | D14: =C17 -> 287000000 | E14: =D17 -> 290500000 | F14: =E17 -> 266000000 | G14: =F17 -> 240450000 | H14: =G17 -> 213850000 | I14: =H17 -> 186200000 | J14: =I17 -> 157500000 | K14: =J17 -> 127750000 | L14: =K17 -> 96950000
B15: Capex | C15: =CHOOSE(Drivers!$C$3,'Fixed asset roll-forward'!$C4,'Fixed asset roll-forward'!$C5,'Fixed asset roll-forward'!$C6)*'Fixed asset roll-forward'!D11 -> 35000000 | D15: =CHOOSE(Drivers!$C$3,'Fixed asset roll-forward'!$C4,'Fixed asset roll-forward'!$C5,'Fixed asset roll-forward'!$C6)*'Fixed asset roll-forward'!E11 -> 35000000 | E15: =CHOOSE(Drivers!$C$3,'Fixed asset roll-forward'!$C4,'Fixed asset roll-forward'!$C5,'Fixed asset roll-forward'!$C6)*'Fixed asset roll-forward'!F11 -> 10500000 | F15: =CHOOSE(Drivers!$C$3,'Fixed asset roll-forward'!$C4,'Fixed asset roll-forward'!$C5,'Fixed asset roll-forward'!$C6)*'Fixed asset roll-forward'!G11 -> 10500000 | G15: =CHOOSE(Drivers!$C$3,'Fixed asset roll-forward'!$C4,'Fixed asset roll-forward'!$C5,'Fixed asset roll-forward'!$C6)*'Fixed asset roll-forward'!H11 -> 10500000 | H15: =CHOOSE(Drivers!$C$3,'Fixed asset roll-forward'!$C4,'Fixed asset roll-forward'!$C5,'Fixed asset roll-forward'!$C6)*'Fixed asset roll-forward'!I11 -> 10500000 | I15: =CHOOSE(Drivers!$C$3,'Fixed asset roll-forward'!$C4,'Fixed asset roll-forward'!$C5,'Fixed asset roll-forward'!$C6)*'Fixed asset roll-forward'!J11 -> 10500000 | J15: =CHOOSE(Drivers!$C$3,'Fixed asset roll-forward'!$C4,'Fixed asset roll-forward'!$C5,'Fixed asset roll-forward'!$C6)*'Fixed asset roll-forward'!K11 -> 10500000 | ... L15: =CHOOSE(Drivers!$C$3,'Fixed asset roll-forward'!$C4,'Fixed asset roll-forward'!$C5,'Fixed asset roll-forward'!$C6)*'Fixed asset roll-forward'!M11 -> 10500000
B16: D&A | C16: =C30 -> -28000000 | D16: =D30 -> -31500000 | E16: =E30 -> -35000000 | F16: =F30 -> -36050000 | G16: =G30 -> -37100000 | H16: =H30 -> -38150000 | I16: =I30 -> -39200000 | J16: =J30 -> -40250000 | ... L16: =L30 -> -42350000
B17: Ending PP&E | C17: =SUM(C14:C16) -> 287000000 | D17: =SUM(D14:D16) -> 290500000 | E17: =SUM(E14:E16) -> 266000000 | F17: =SUM(F14:F16) -> 240450000 | G17: =SUM(G14:G16) -> 213850000 | H17: =SUM(H14:H16) -> 186200000 | I17: =SUM(I14:I16) -> 157500000 | J17: =SUM(J14:J16) -> 127750000 | ... L17: =SUM(L14:L16) -> 65100000
B19: D&A schedule (in EUR) | C19: 1 | D19: 2 | E19: 3 | F19: 4 | G19: 5 | H19: 6 | I19: 7 | J19: 8 | K19: 9 | L19: 10
B20: Capex Year 1 | C20: =-$C$14/10 -> -28000000 | D20: =-$C$14/10 -> -28000000 | E20: =-$C$14/10 -> -28000000 | F20: =-$C$14/10 -> -28000000 | G20: =-$C$14/10 -> -28000000 | H20: =-$C$14/10 -> -28000000 | I20: =-$C$14/10 -> -28000000 | J20: =-$C$14/10 -> -28000000 | ... L20: =-$C$14/10 -> -28000000
B21: Capex Year 2 | D21: =-$C$15/10 -> -3500000 | E21: =-$C$15/10 -> -3500000 | F21: =-$C$15/10 -> -3500000 | G21: =-$C$15/10 -> -3500000 | H21: =-$C$15/10 -> -3500000 | I21: =-$C$15/10 -> -3500000 | J21: =-$C$15/10 -> -3500000 | K21: =-$C$15/10 -> -3500000 | L21: =-$C$15/10 -> -3500000
B22: Capex Year 3 | E22: =-$D$15/10 -> -3500000 | F22: =-$D$15/10 -> -3500000 | G22: =-$D$15/10 -> -3500000 | H22: =-$D$15/10 -> -3500000 | I22: =-$D$15/10 -> -3500000 | J22: =-$D$15/10 -> -3500000 | K22: =-$D$15/10 -> -3500000 | L22: =-$D$15/10 -> -3500000
B23: Capex Year 4 | F23: =-$E$15/10 -> -1050000 | G23: =-$E$15/10 -> -1050000 | H23: =-$E$15/10 -> -1050000 | I23: =-$E$15/10 -> -1050000 | J23: =-$E$15/10 -> -1050000 | K23: =-$E$15/10 -> -1050000 | L23: =-$E$15/10 -> -1050000
B24: Capex Year 5 | G24: =-$F$15/10 -> -1050000 | H24: =-$F$15/10 -> -1050000 | I24: =-$F$15/10 -> -1050000 | J24: =-$F$15/10 -> -1050000 | K24: =-$F$15/10 -> -1050000 | L24: =-$F$15/10 -> -1050000
B25: Capex Year 6 | H25: =-$G$15/10 -> -1050000 | I25: =-$G$15/10 -> -1050000 | J25: =-$G$15/10 -> -1050000 | K25: =-$G$15/10 -> -1050000 | L25: =-$G$15/10 -> -1050000
B26: Capex Year 7 | I26: =-$H$15/10 -> -1050000 | J26: =-$H$15/10 -> -1050000 | K26: =-$H$15/10 -> -1050000 | L26: =-$H$15/10 -> -1050000
B27: Capex Year 8 | J27: =-$I$15/10 -> -1050000 | K27: =-$I$15/10 -> -1050000 | L27: =-$I$15/10 -> -1050000
B28: Capex Year 9 | K28: =-$J$15/10 -> -1050000 | L28: =-$J$15/10 -> -1050000
B29: Capex Year 10 | L29: =-$K$15/10 -> -1050000
B30: D&A | C30: =SUM(C20:C29) -> -28000000 | D30: =SUM(D20:D29) -> -31500000 | E30: =SUM(E20:E29) -> -35000000 | F30: =SUM(F20:F29) -> -36050000 | G30: =SUM(G20:G29) -> -37100000 | H30: =SUM(H20:H29) -> -38150000 | I30: =SUM(I20:I29) -> -39200000 | J30: =SUM(J20:J29) -> -40250000 | ... L30: =SUM(L20:L29) -> -42350000

Sheet Working capital
B1: Working capital
B3: WC Italy
B4: DIO | C4: =Drivers!C21 -> 25
B5: DPO | C5: =Drivers!C22 -> 30
B6: Net Trading Cycle (days) | C6: =C4-C5 -> -5
B8: WC Vietnam
B9: DIO | C9: =CHOOSE(Drivers!$C$3,'Working capital'!C20,'Working capital'!C21,'Working capital'!C22) -> 50
B10: DPO | C10: =CHOOSE(Drivers!$C$3,'Working capital'!C25,'Working capital'!C26,'Working capital'!C27) -> 30
B11: Net Trading Cycle (days) | C11: =C9-C10 -> 20
B13: in EUR | C13: 1 | D13: 2 | E13: 3 | F13: 4 | G13: 5 | H13: 6 | I13: 7 | J13: 8 | K13: 9 | L13: 10
B14: Extra production value | C14: ='Savings forecast'!C24*'Savings forecast'!C11 -> 176000000 | D14: ='Savings forecast'!D24*'Savings forecast'!D11 -> 192610000 | E14: ='Savings forecast'!E24*'Savings forecast'!E11 -> 203056260 | F14: ='Savings forecast'!F24*'Savings forecast'!F11 -> 216359946 | G14: ='Savings forecast'!G24*'Savings forecast'!G11 -> 2.1789851e+08 | H14: ='Savings forecast'!H24*'Savings forecast'!H11 -> 2.2188506e+08 | I14: ='Savings forecast'!I24*'Savings forecast'!I11 -> 2.2328778e+08 | J14: ='Savings forecast'!J24*'Savings forecast'!J11 -> 2.2457497e+08 | ... L14: ='Savings forecast'!L24*'Savings forecast'!L11 -> 2.3251058e+08
B15: Delta net trading cycle (days) | C15: =$C$11-$C$6 -> 25 | D15: =$C$11-$C$6 -> 25 | E15: =$C$11-$C$6 -> 25 | F15: =$C$11-$C$6 -> 25 | G15: =$C$11-$C$6 -> 25 | H15: =$C$11-$C$6 -> 25 | I15: =$C$11-$C$6 -> 25 | J15: =$C$11-$C$6 -> 25 | ... L15: =$C$11-$C$6 -> 25
B16: Working capital | C16: =-C14*C15/360 -> -12222222 | D16: =-D14*D15/360 -> -13375694 | E16: =-E14*E15/360 -> -14101129 | F16: =-F14*F15/360 -> -15024996 | G16: =-G14*G15/360 -> -15131841 | H16: =-H14*H15/360 -> -15408685 | I16: =-I14*I15/360 -> -15506096 | J16: =-J14*J15/360 -> -15595484 | ... L16: =-L14*L15/360 -> -16146568
B17: Delta Working Capital | C17: =C16 -> -12222222 | D17: =D16-C16 -> -1153472.2 | E17: =E16-D16 -> -725434.72 | F17: =F16-E16 -> -923867.08 | G17: =G16-F16 -> -106844.42 | H17: =H16-G16 -> -276843.9 | I17: =I16-H16 -> -97411.224 | J17: =J16-I16 -> -89388.082 | K17: =K16-J16 -> -274330.2 | L17: =L16-K16 -> -276754.07
B19: DIO Vietnam
B20: Best case | C20: 45
B21: Base case | C21: 50
B22: Worst case | C22: 55
B24: DPO Vietnam
B25: Best case | C25: 25
B26: Base case | C26: 30
B27: Worst case | C27: 35

Sheet Financing
B1: Financing
B3: Investment in Year 0 | C3: ='Fixed asset roll-forward'!$C$14 -> 280000000
B5: Financing facilities
B6: Debt Facility (million EUR) | C6: =Drivers!C28 -> 200000000
B7: Interest rate Debt Facility | C7: =Drivers!C29 -> 0.05
B8: Repay Debt Facility in | C8: 10 years
B10: in EUR | C10: 0 | D10: 1 | E10: 2 | F10: 3 | G10: 4 | H10: 5 | I10: 6 | J10: 7 | K10: 8 | L10: 9 | M10: 10
B11: Beginning Debt | C11: =C6 -> 200000000 | D11: =C14 -> 200000000 | E11: =D14 -> 200000000 | F11: =E14 -> 190000000 | G11: =F14 -> 170000000 | H11: =G14 -> 150000000 | I11: =H14 -> 130000000 | J11: =I14 -> 110000000 | K11: =J14 -> 90000000 | ... M11: =L14 -> 50000000
B12: Repayment | C12: =-$C$11*C13 -> 0 | D12: =-$D$11*D13 -> 0 | E12: =-$D$11*E13 -> -10000000 | F12: =-$D$11*F13 -> -20000000 | G12: =-$D$11*G13 -> -20000000 | H12: =-$D$11*H13 -> -20000000 | I12: =-$D$11*I13 -> -20000000 | J12: =-$D$11*J13 -> -20000000 | K12: =-$D$11*K13 -> -20000000 | ... M12: =-$D$11*M13 -> -20000000
B13: Repayment % | C13: 0 | D13: 0 | E13: 0.05 | F13: 0.1 | G13: 0.1 | H13: 0.1 | I13: 0.1 | J13: 0.1 | K13: 0.1 | L13: 0.1 | M13: 0.1
B14: Ending Debt | C14: =SUM(C11:C12) -> 200000000 | D14: =SUM(D11:D12) -> 200000000 | E14: =SUM(E11:E12) -> 190000000 | F14: =SUM(F11:F12) -> 170000000 | G14: =SUM(G11:G12) -> 150000000 | H14: =SUM(H11:H12) -> 130000000 | I14: =SUM(I11:I12) -> 110000000 | J14: =SUM(J11:J12) -> 90000000 | ... M14: =SUM(M11:M12) -> 30000000
B16: Interest expense | C16: =IF(C10=0,0,-C11*$C$7) -> 0 | D16: =IF(D10=0,0,-D11*$C$7) -> -10000000 | E16: =IF(E10=0,0,-E11*$C$7) -> -10000000 | F16: =IF(F10=0,0,-F11*$C$7) -> -9500000 | G16: =IF(G10=0,0,-G11*$C$7) -> -8500000 | H16: =IF(H10=0,0,-H11*$C$7) -> -7500000 | I16: =IF(I10=0,0,-I11*$C$7) -> -6500000 | J16: =IF(J10=0,0,-J11*$C$7) -> -5500000 | ... M16: =IF(M10=0,0,-M11*$C$7) -> -2500000
B18: Volume | C18: 0 | D18: ='Savings forecast'!C11 -> 16000 | E18: ='Savings forecast'!D11 -> 17000 | F18: ='Savings forecast'!E11 -> 17400 | G18: ='Savings forecast'!F11 -> 18000 | H18: ='Savings forecast'!G11 -> 17600 | I18: ='Savings forecast'!H11 -> 17400 | J18: ='Savings forecast'!I11 -> 17000 | K18: ='Savings forecast'!J11 -> 16600 | ... M18: ='Savings forecast'!L11 -> 16200
B19: Volume lower than 16,000? | C19: =IF(C18<16000,"Yes","No") -> Yes | D19: =IF(D18<16000,"Yes","No") -> No | E19: =IF(E18<16000,"Yes","No") -> No | F19: =IF(F18<16000,"Yes","No") -> No | G19: =IF(G18<16000,"Yes","No") -> No | H19: =IF(H18<16000,"Yes","No") -> No | I19: =IF(I18<16000,"Yes","No") -> No | J19: =IF(J18<16000,"Yes","No") -> No | ... M19: =IF(M18<16000,"Yes","No") -> No
B20: Covenant Penalty | C20: =IF(C10=0,0,IF(C19="Yes",1000000,0)) -> 0 | D20: =IF(D10=0,0,IF(D19="Yes",1000000,0)) -> 0 | E20: =IF(E10=0,0,IF(E19="Yes",1000000,0)) -> 0 | F20: =IF(F10=0,0,IF(F19="Yes",1000000,0)) -> 0 | G20: =IF(G10=0,0,IF(G19="Yes",1000000,0)) -> 0 | H20: =IF(H10=0,0,IF(H19="Yes",1000000,0)) -> 0 | I20: =IF(I10=0,0,IF(I19="Yes",1000000,0)) -> 0 | J20: =IF(J10=0,0,IF(J19="Yes",1000000,0)) -> 0 | ... M20: =IF(M10=0,0,IF(M19="Yes",1000000,0)) -> 0
B22: Net Cash Flow | C22: ='Cash Flow'!C12 -> -280000000 | D22: ='Cash Flow'!D12 -> 4577777.8 | E22: ='Cash Flow'!E12 -> 7764027.8 | F22: ='Cash Flow'!F12 -> 23069862 | G22: ='Cash Flow'!G12 -> 23206956 | H22: ='Cash Flow'!H12 -> 21457943 | I22: ='Cash Flow'!I12 -> 19218803 | J22: ='Cash Flow'!J12 -> 16808535 | ... M22: ='Cash Flow'!M12 -> 8837036.5
B23: Equity financing | C23: =-(C14+C22) -> 80000000 | D23: =IF(D22>0,C23,C23-D22) -> 80000000 | E23: =IF(E22>0,D23,D23-E22) -> 80000000 | F23: =IF(F22>0,E23,E23-F22) -> 80000000 | G23: =IF(G22>0,F23,F23-G22) -> 80000000 | H23: =IF(H22>0,G23,G23-H22) -> 80000000 | I23: =IF(I22>0,H23,H23-I22) -> 80000000 | J23: =IF(J22>0,I23,I23-J22) -> 80000000 | K23: =IF(K22>0,J23,J23-K22) -> 80000000 | ... M23: =IF(M22>0,L23,L23-M22) -> 80000000

Sheet P&L
B1: P&L
B3: in EUR | C3: 1 | D3: 2 | E3: 3 | F3: 4 | G3: 5 | H3: 6 | I3: 7 | J3: 8 | K3: 9 | L3: 10
B4: Savings (EBITDA) | C4: ='Savings forecast'!C31 -> 72000000 | D4: ='Savings forecast'!D31 -> 73525000 | E4: ='Savings forecast'!E31 -> 72064710 | F4: ='Savings forecast'!F31 -> 71094033 | G4: ='Savings forecast'!G31 -> 65978268 | H4: ='Savings forecast'!H31 -> 61572353 | I4: ='Savings forecast'!I31 -> 56422780 | J4: ='Savings forecast'!J31 -> 51285458 | ... L4: ='Savings forecast'!L31 -> 42113791
B5: D&A | C5: ='Fixed asset roll-forward'!C16 -> -28000000 | D5: ='Fixed asset roll-forward'!D16 -> -31500000 | E5: ='Fixed asset roll-forward'!E16 -> -35000000 | F5: ='Fixed asset roll-forward'!F16 -> -36050000 | G5: ='Fixed asset roll-forward'!G16 -> -37100000 | H5: ='Fixed asset roll-forward'!H16 -> -38150000 | I5: ='Fixed asset roll-forward'!I16 -> -39200000 | J5: ='Fixed asset roll-forward'!J16 -> -40250000 | ... L5: ='Fixed asset roll-forward'!L16 -> -42350000
B6: EBIT | C6: =SUM(C4:C5) -> 44000000 | D6: =SUM(D4:D5) -> 42025000 | E6: =SUM(E4:E5) -> 37064710 | F6: =SUM(F4:F5) -> 35044033 | G6: =SUM(G4:G5) -> 28878268 | H6: =SUM(H4:H5) -> 23422353 | I6: =SUM(I4:I5) -> 17222780 | J6: =SUM(J4:J5) -> 11035458 | ... L6: =SUM(L4:L5) -> -236209.39
B7: Interest expenses | C7: =Financing!D16 -> -10000000 | D7: =Financing!E16 -> -10000000 | E7: =Financing!F16 -> -9500000 | F7: =Financing!G16 -> -8500000 | G7: =Financing!H16 -> -7500000 | H7: =Financing!I16 -> -6500000 | I7: =Financing!J16 -> -5500000 | J7: =Financing!K16 -> -4500000 | ... L7: =Financing!M16 -> -2500000
B8: Covenants | C8: =-Financing!D20 -> 0 | D8: =-Financing!E20 -> 0 | E8: =-Financing!F20 -> 0 | F8: =-Financing!G20 -> 0 | G8: =-Financing!H20 -> 0 | H8: =-Financing!I20 -> 0 | I8: =-Financing!J20 -> 0 | J8: =-Financing!K20 -> 0 | ... L8: =-Financing!M20 -> 0
B9: EBT | C9: =SUM(C6:C8) -> 34000000 | D9: =SUM(D6:D8) -> 32025000 | E9: =SUM(E6:E8) -> 27564710 | F9: =SUM(F6:F8) -> 26544033 | G9: =SUM(G6:G8) -> 21378268 | H9: =SUM(H6:H8) -> 16922353 | I9: =SUM(I6:I8) -> 11722780 | J9: =SUM(J6:J8) -> 6535458.3 | ... L9: =SUM(L6:L8) -> -2736209.4
B10: Taxes | C10: =IF(-'P&L'!C9*Drivers!$C$37>0,0,-'P&L'!C9*Drivers!$C$37) -> -10200000 | D10: =IF(-'P&L'!D9*Drivers!$C$37>0,0,-'P&L'!D9*Drivers!$C$37) -> -9607500 | E10: =IF(-'P&L'!E9*Drivers!$C$37>0,0,-'P&L'!E9*Drivers!$C$37) -> -8269413 | F10: =IF(-'P&L'!F9*Drivers!$C$37>0,0,-'P&L'!F9*Drivers!$C$37) -> -7963209.9 | G10: =IF(-'P&L'!G9*Drivers!$C$37>0,0,-'P&L'!G9*Drivers!$C$37) -> -6413480.5 | H10: =IF(-'P&L'!H9*Drivers!$C$37>0,0,-'P&L'!H9*Drivers!$C$37) -> -5076705.8 | I10: =IF(-'P&L'!I9*Drivers!$C$37>0,0,-'P&L'!I9*Drivers!$C$37) -> -3516834.1 | J10: =IF(-'P&L'!J9*Drivers!$C$37>0,0,-'P&L'!J9*Drivers!$C$37) -> -1960637.5 | ... L10: =IF(-'P&L'!L9*Drivers!$C$37>0,0,-'P&L'!L9*Drivers!$C$37) -> 0
B11: Net Income | C11: =SUM(C9:C10) -> 23800000 | D11: =SUM(D9:D10) -> 22417500 | E11: =SUM(E9:E10) -> 19295297 | F11: =SUM(F9:F10) -> 18580823 | G11: =SUM(G9:G10) -> 14964788 | H11: =SUM(H9:H10) -> 11845647 | I11: =SUM(I9:I10) -> 8205946.2 | J11: =SUM(J9:J10) -> 4574820.8 | ... L11: =SUM(L9:L10) -> -2736209.4

Sheet Cash Flow
B1: Cash Flow
B3: in EUR | C3: 0 | D3: 1 | E3: 2 | F3: 3 | G3: 4 | H3: 5 | I3: 6 | J3: 7 | K3: 8 | L3: 9 | M3: 10 | O3: Residual Value
B4: Savings per unit (EBITDA) | C4: 0 | D4: ='Savings forecast'!C31 -> 72000000 | E4: ='Savings forecast'!D31 -> 73525000 | F4: ='Savings forecast'!E31 -> 72064710 | G4: ='Savings forecast'!F31 -> 71094033 | H4: ='Savings forecast'!G31 -> 65978268 | I4: ='Savings forecast'!H31 -> 61572353 | J4: ='Savings forecast'!I31 -> 56422780 | K4: ='Savings forecast'!J31 -> 51285458 | ... M4: ='Savings forecast'!L31 -> 42113791
B5: Taxes | C5: 0 | D5: ='P&L'!C10 -> -10200000 | E5: ='P&L'!D10 -> -9607500 | F5: ='P&L'!E10 -> -8269413 | G5: ='P&L'!F10 -> -7963209.9 | H5: ='P&L'!G10 -> -6413480.5 | I5: ='P&L'!H10 -> -5076705.8 | J5: ='P&L'!I10 -> -3516834.1 | K5: ='P&L'!J10 -> -1960637.5 | ... M5: ='P&L'!L10 -> 0
B6: Delta Working Capital | C6: 0 | D6: ='Working capital'!C17 -> -12222222 | E6: ='Working capital'!D17 -> -1153472.2 | F6: ='Working capital'!E17 -> -725434.72 | G6: ='Working capital'!F17 -> -923867.08 | H6: ='Working capital'!G17 -> -106844.42 | I6: ='Working capital'!H17 -> -276843.9 | J6: ='Working capital'!I17 -> -97411.224 | K6: ='Working capital'!J17 -> -89388.082 | ... M6: ='Working capital'!L17 -> -276754.07
B7: Capex | C7: =-'Fixed asset roll-forward'!C14 -> -280000000 | D7: =-'Fixed asset roll-forward'!C15 -> -35000000 | E7: =-'Fixed asset roll-forward'!D15 -> -35000000 | F7: =-'Fixed asset roll-forward'!E15 -> -10500000 | G7: =-'Fixed asset roll-forward'!F15 -> -10500000 | H7: =-'Fixed asset roll-forward'!G15 -> -10500000 | I7: =-'Fixed asset roll-forward'!H15 -> -10500000 | J7: =-'Fixed asset roll-forward'!I15 -> -10500000 | K7: =-'Fixed asset roll-forward'!J15 -> -10500000 | ... M7: =-'Fixed asset roll-forward'!L15 -> -10500000
B8: Operating Cash Flow | C8: =SUM(C4:C7) -> -280000000 | D8: =SUM(D4:D7) -> 14577778 | E8: =SUM(E4:E7) -> 27764028 | F8: =SUM(F4:F7) -> 52569862 | G8: =SUM(G4:G7) -> 51706956 | H8: =SUM(H4:H7) -> 48957943 | I8: =SUM(I4:I7) -> 45718803 | J8: =SUM(J4:J7) -> 42308535 | ... M8: =SUM(M4:M7) -> 31337037
B9: Debt repayment | C9: 0 | D9: =Financing!D12 -> 0 | E9: =Financing!E12 -> -10000000 | F9: =Financing!F12 -> -20000000 | G9: =Financing!G12 -> -20000000 | H9: =Financing!H12 -> -20000000 | I9: =Financing!I12 -> -20000000 | J9: =Financing!J12 -> -20000000 | K9: =Financing!K12 -> -20000000 | ... M9: =Financing!M12 -> -20000000
B10: Interest expenses | C10: 0 | D10: =Financing!D16 -> -10000000 | E10: =Financing!E16 -> -10000000 | F10: =Financing!F16 -> -9500000 | G10: =Financing!G16 -> -8500000 | H10: =Financing!H16 -> -7500000 | I10: =Financing!I16 -> -6500000 | J10: =Financing!J16 -> -5500000 | K10: =Financing!K16 -> -4500000 | ... M10: =Financing!M16 -> -2500000
B11: Covenant penalty | C11: 0 | D11: =-Financing!D20 -> 0 | E11: =-Financing!E20 -> 0 | F11: =-Financing!F20 -> 0 | G11: =-Financing!G20 -> 0 | H11: =-Financing!H20 -> 0 | I11: =-Financing!I20 -> 0 | J11: =-Financing!J20 -> 0 | K11: =-Financing!K20 -> 0 | ... M11: =-Financing!M20 -> 0
B12: Net Cash Flow | C12: =SUM(C8:C11) -> -280000000 | D12: =SUM(D8:D11) -> 4577777.8 | E12: =SUM(E8:E11) -> 7764027.8 | F12: =SUM(F8:F11) -> 23069862 | G12: =SUM(G8:G11) -> 23206956 | H12: =SUM(H8:H11) -> 21457943 | I12: =SUM(I8:I11) -> 19218803 | J12: =SUM(J8:J11) -> 16808535 | ... M12: =SUM(M8:M11) -> 8837036.5 | O12: =Drivers!C39 -> 100000000

Sheet WACC
B1: WACC
B3: Cost of debt | C3: =Drivers!C29 -> 0.05
B4: Risk-free in Vietnam | C4: =Drivers!C49 -> 0.03
B5: Tax rate | C5: =Drivers!C37 -> 0.3
B6: Market risk premium in Vietnam | C6: =Drivers!C46 -> 0.06
B8: Comparable companies | C8: Leverage (D/E) | D8: Beta
B9: Company A | C9: =Drivers!C42 -> 0.8 | D9: =Drivers!D42 -> 0.6
B10: Company B | C10: =Drivers!C43 -> 0.9 | D10: =Drivers!D43 -> 0.65
B11: Company C | C11: =Drivers!C44 -> 0.85 | D11: =Drivers!D44 -> 0.57
B14: in EUR | C14: 0 | D14: 1 | E14: 2 | F14: 3 | G14: 4 | H14: 5 | I14: 6 | J14: 7 | K14: 8 | L14: 9 | M14: 10
B15: Debt financing | C15: =Financing!C14 -> 200000000 | D15: =Financing!D14 -> 200000000 | E15: =Financing!E14 -> 190000000 | F15: =Financing!F14 -> 170000000 | G15: =Financing!G14 -> 150000000 | H15: =Financing!H14 -> 130000000 | I15: =Financing!I14 -> 110000000 | J15: =Financing!J14 -> 90000000 | ... M15: =Financing!M14 -> 30000000
B16: Equity financing | C16: =Financing!C23 -> 80000000 | D16: =Financing!D23 -> 80000000 | E16: =Financing!E23 -> 80000000 | F16: =Financing!F23 -> 80000000 | G16: =Financing!G23 -> 80000000 | H16: =Financing!H23 -> 80000000 | I16: =Financing!I23 -> 80000000 | J16: =Financing!J23 -> 80000000 | ... M16: =Financing!M23 -> 80000000
B17: Total financing | C17: =SUM(C15:C16) -> 280000000 | D17: =SUM(D15:D16) -> 280000000 | E17: =SUM(E15:E16) -> 270000000 | F17: =SUM(F15:F16) -> 250000000 | G17: =SUM(G15:G16) -> 230000000 | H17: =SUM(H15:H16) -> 210000000 | I17: =SUM(I15:I16) -> 190000000 | J17: =SUM(J15:J16) -> 170000000 | ... M17: =SUM(M15:M16) -> 110000000
B19: Debt financing % | C19: =C15/C$17 -> 0.71428571 | D19: =D15/D$17 -> 0.71428571 | E19: =E15/E$17 -> 0.7037037 | F19: =F15/F$17 -> 0.68 | G19: =G15/G$17 -> 0.65217391 | H19: =H15/H$17 -> 0.61904762 | I19: =I15/I$17 -> 0.57894737 | J19: =J15/J$17 -> 0.52941176 | ... M19: =M15/M$17 -> 0.27272727
B20: Equity financing % | C20: =C16/C$17 -> 0.28571429 | D20: =D16/D$17 -> 0.28571429 | E20: =E16/E$17 -> 0.2962963 | F20: =F16/F$17 -> 0.32 | G20: =G16/G$17 -> 0.34782609 | H20: =H16/H$17 -> 0.38095238 | I20: =I16/I$17 -> 0.42105263 | J20: =J16/J$17 -> 0.47058824 | ... M20: =M16/M$17 -> 0.72727273
B21: Total financing % | C21: =SUM(C19:C20) -> 1 | D21: =SUM(D19:D20) -> 1 | E21: =SUM(E19:E20) -> 1 | F21: =SUM(F19:F20) -> 1 | G21: =SUM(G19:G20) -> 1 | H21: =SUM(H19:H20) -> 1 | I21: =SUM(I19:I20) -> 1 | J21: =SUM(J19:J20) -> 1 | ... M21: =SUM(M19:M20) -> 1
B24: Comparable companies:
B25: Average leverage | C25: =AVERAGE(C9:C11) -> 0.85
B26: Average beta | C26: =AVERAGE(D9:D11) -> 0.60666667
B28: Project beta:
B29: Debt / Equity | C29: =C19/C20 -> 2.5 | D29: =D19/D20 -> 2.5 | E29: =E19/E20 -> 2.375 | F29: =F19/F20 -> 2.125 | G29: =G19/G20 -> 1.875 | H29: =H19/H20 -> 1.625 | I29: =I19/I20 -> 1.375 | J29: =J19/J20 -> 1.125 | ... M29: =M19/M20 -> 0.375
B30: Beta unlevered | C30: =$C$26/((1+(1-$C$5)*($C$25))) -> 0.38035528 | D30: =$C$26/((1+(1-$C$5)*($C$25))) -> 0.38035528 | E30: =$C$26/((1+(1-$C$5)*($C$25))) -> 0.38035528 | F30: =$C$26/((1+(1-$C$5)*($C$25))) -> 0.38035528 | G30: =$C$26/((1+(1-$C$5)*($C$25))) -> 0.38035528 | H30: =$C$26/((1+(1-$C$5)*($C$25))) -> 0.38035528 | I30: =$C$26/((1+(1-$C$5)*($C$25))) -> 0.38035528 | J30: =$C$26/((1+(1-$C$5)*($C$25))) -> 0.38035528 | ... M30: =$C$26/((1+(1-$C$5)*($C$25))) -> 0.38035528
B31: Project beta: | C31: =C30*(1+(1-$C$5)*(C29)) -> 1.045977 | D31: =D30*(1+(1-$C$5)*(D29)) -> 1.045977 | E31: =E30*(1+(1-$C$5)*(E29)) -> 1.0126959 | F31: =F30*(1+(1-$C$5)*(F29)) -> 0.94613375 | G31: =G30*(1+(1-$C$5)*(G29)) -> 0.87957158 | H31: =H30*(1+(1-$C$5)*(H29)) -> 0.8130094 | I31: =I30*(1+(1-$C$5)*(I29)) -> 0.74644723 | J31: =J30*(1+(1-$C$5)*(J29)) -> 0.67988506 | ... M31: =M30*(1+(1-$C$5)*(M29)) -> 0.48019854
B33: Cost of equity | C33: =$C$4+$C$6*C31 -> 0.092758621 | D33: =$C$4+$C$6*D31 -> 0.092758621 | E33: =$C$4+$C$6*E31 -> 0.090761755 | F33: =$C$4+$C$6*F31 -> 0.086768025 | G33: =$C$4+$C$6*G31 -> 0.082774295 | H33: =$C$4+$C$6*H31 -> 0.078780564 | I33: =$C$4+$C$6*I31 -> 0.074786834 | J33: =$C$4+$C$6*J31 -> 0.070793103 | ... M33: =$C$4+$C$6*M31 -> 0.058811912
B35: WACC | C35: =C19*(1-$C$5)*$C$3+C20*C33 -> 0.051502463 | D35: =D19*(1-$C$5)*$C$3+D20*D33 -> 0.051502463 | E35: =E19*(1-$C$5)*$C$3+E20*E33 -> 0.051522002 | F35: =F19*(1-$C$5)*$C$3+F20*F33 -> 0.051565768 | G35: =G19*(1-$C$5)*$C$3+G20*G33 -> 0.051617146 | H35: =H19*(1-$C$5)*$C$3+H20*H33 -> 0.05167831 | I35: =I19*(1-$C$5)*$C$3+I20*I33 -> 0.051752351 | J35: =J19*(1-$C$5)*$C$3+J20*J33 -> 0.051843813 | ... M35: =M19*(1-$C$5)*$C$3+M20*M33 -> 0.052317754

Sheet Output -->
B17: Output -->

Sheet Discounted Cash Flows
B1: Discounted Cash Flows
B3: Selected case | C3: 2
B5: Residual Value | C5: =Drivers!C39-Financing!M14 -> 70000000
B7: in EUR | D7: 0 | E7: 1 | F7: 2 | G7: 3 | H7: 4 | I7: 5 | J7: 6 | K7: 7 | L7: 8 | M7: 9 | N7: 10 | O7: Residual Value
B8: Net Cash Flow | D8: =-Financing!C23 -> -80000000 | E8: ='Cash Flow'!D12 -> 4577777.8 | F8: ='Cash Flow'!E12 -> 7764027.8 | G8: ='Cash Flow'!F12 -> 23069862 | H8: ='Cash Flow'!G12 -> 23206956 | I8: ='Cash Flow'!H12 -> 21457943 | J8: ='Cash Flow'!I12 -> 19218803 | K8: ='Cash Flow'!J12 -> 16808535 | L8: ='Cash Flow'!K12 -> 14235433 | ... N8: ='Cash Flow'!M12 -> 8837036.5 | O8: =C5 -> 70000000
B10: Cost of equity | E10: =WACC!D33 -> 0.092758621 | F10: =WACC!E33 -> 0.090761755 | G10: =WACC!F33 -> 0.086768025 | H10: =WACC!G33 -> 0.082774295 | I10: =WACC!H33 -> 0.078780564 | J10: =WACC!I33 -> 0.074786834 | K10: =WACC!J33 -> 0.070793103 | L10: =WACC!K33 -> 0.066799373 | ... N10: =WACC!M33 -> 0.058811912
B11: Discounted Cash Flow | D11: =D8/(1+D10)^D7 -> -80000000 | E11: =E8/(1+E10)^E7 -> 4189193.9 | F11: =F8/(1+F10)^F7 -> 6525702.6 | G11: =G8/(1+G10)^G7 -> 17973574 | H11: =H8/(1+H10)^H7 -> 16883654 | I11: =I8/(1+I10)^I7 -> 14686643 | J11: =J8/(1+J10)^J7 -> 12467871 | K11: =K8/(1+K10)^K7 -> 10413360 | ... N11: =N8/(1+N10)^N7 -> 4990205.9
B12: Present Value Residual Value | N12: =O8/(1+N10)^N7 -> 39528456
B13: Discounted Cash Flow with Residual Value | D13: =SUM(D11:D12) -> -80000000 | E13: =SUM(E11:E12) -> 4189193.9 | F13: =SUM(F11:F12) -> 6525702.6 | G13: =SUM(G11:G12) -> 17973574 | H13: =SUM(H11:H12) -> 16883654 | I13: =SUM(I11:I12) -> 14686643 | J13: =SUM(J11:J12) -> 12467871 | K13: =SUM(K11:K12) -> 10413360 | ... N13: =SUM(N11:N12) -> 44518662
