Workbook

Sheet Original Source
B3: Date | C3: Financials | D3: Amount
B4: 1.1.2014 | C4: Revenue - Supermarkets | D4: 72
B5: 1.1.2014 | C5: Cogs - Supermarkets | D5: 47
B6: 1.1.2014 | C6: Revenue - Discounters | D6: 37
B7: 1.1.2014 | C7: Cogs - Discounters | D7: 20
B8: 1.1.2014 | C8: Revenue - Grocery | D8: 36
B9: 1.1.2014 | C9: Cogs - Grocery | D9: 17
B10: 1.1.2014 | C10: Revenue - Retail | D10: 57
B11: 1.1.2014 | C11: Cogs - Retail | D11: 32
B12: 1.1.2014 | C12: Operating expenses | D12: 95.4
B13: 1.1.2014 | C13: D&A | D13: 2
B14: 1.1.2014 | C14: Interest expenses | D14: 5
B15: 1.1.2014 | C15: Taxes | D15: 17.29
... B438: 12.1.2016 | C438: Other revenue | D438: 628

Sheet Exercise -->
B13: Exercise -->

Sheet Workings
B3: Date | C3: Year | D3: Financials | E3: Amount | F3: Mapping
B4: 41640 | C4: =YEAR(B4) -> 2014 | D4: Revenue - Supermarkets | E4: 72 | F4: Revenue
B5: 41640 | C5: =YEAR(B5) -> 2014 | D5: Cogs - Supermarkets | E5: 47 | F5: Cost of goods sold
B6: 41640 | C6: =YEAR(B6) -> 2014 | D6: Revenue - Discounters | E6: 37 | F6: Revenue
B7: 41640 | C7: =YEAR(B7) -> 2014 | D7: Cogs - Discounters | E7: 20 | F7: Cost of goods sold
B8: 41640 | C8: =YEAR(B8) -> 2014 | D8: Revenue - Grocery | E8: 36 | F8: Revenue
B9: 41640 | C9: =YEAR(B9) -> 2014 | D9: Cogs - Grocery | E9: 17 | F9: Cost of goods sold
B10: 41640 | C10: =YEAR(B10) -> 2014 | D10: Revenue - Retail | E10: 57 | F10: Revenue
B11: 41640 | C11: =YEAR(B11) -> 2014 | D11: Cogs - Retail | E11: 32 | F11: Cost of goods sold
B12: 41640 | C12: =YEAR(B12) -> 2014 | D12: Operating expenses | E12: 95.4 | F12: Operating expenses
B13: 41640 | C13: =YEAR(B13) -> 2014 | D13: D&A | E13: 2 | F13: D&A
B14: 41640 | C14: =YEAR(B14) -> 2014 | D14: Interest expenses | E14: 5 | F14: Interest expenses
B15: 41640 | C15: =YEAR(B15) -> 2014 | D15: Taxes | E15: 17.29 | F15: Taxes
... B438: 42705 | C438: =YEAR(B438) -> 2016 | D438: Other revenue | E438: 628 | F438: Revenue

Sheet P&L
B1: P&L
B3: $ in million | C3: 2014 | D3: 2015 | E3: 2016
B4: Revenue | C4: =+SUMIFS(Workings!$E:$E,Workings!$F:$F,'P&L'!$B4,Workings!$C:$C,'P&L'!C$3) -> 2922 | D4: =+SUMIFS(Workings!$E:$E,Workings!$F:$F,'P&L'!$B4,Workings!$C:$C,'P&L'!D$3) -> 2984 | E4: =+SUMIFS(Workings!$E:$E,Workings!$F:$F,'P&L'!$B4,Workings!$C:$C,'P&L'!E$3) -> 3040
B5: Cost of goods sold | C5: =-1*SUMIFS(Workings!$E:$E,Workings!$F:$F,'P&L'!$B5,Workings!$C:$C,'P&L'!C$3) -> -1401 | D5: =-1*SUMIFS(Workings!$E:$E,Workings!$F:$F,'P&L'!$B5,Workings!$C:$C,'P&L'!D$3) -> -1383 | E5: =-1*SUMIFS(Workings!$E:$E,Workings!$F:$F,'P&L'!$B5,Workings!$C:$C,'P&L'!E$3) -> -1367
B6: Gross Profit | C6: =SUM(C4:C5) -> 1521 | D6: =SUM(D4:D5) -> 1601 | E6: =SUM(E4:E5) -> 1673
B7: Operating expenses | C7: =-1*SUMIFS(Workings!$E:$E,Workings!$F:$F,'P&L'!$B7,Workings!$C:$C,'P&L'!C$3) -> -1212.18 | D7: =-1*SUMIFS(Workings!$E:$E,Workings!$F:$F,'P&L'!$B7,Workings!$C:$C,'P&L'!D$3) -> -1245.34 | E7: =-1*SUMIFS(Workings!$E:$E,Workings!$F:$F,'P&L'!$B7,Workings!$C:$C,'P&L'!E$3) -> -1068.24
B8: EBITDA | C8: =SUM(C6:C7) -> 308.82 | D8: =SUM(D6:D7) -> 355.66 | E8: =SUM(E6:E7) -> 604.76
B9: D&A | C9: =-1*SUMIFS(Workings!$E:$E,Workings!$F:$F,'P&L'!$B9,Workings!$C:$C,'P&L'!C$3) -> -31 | D9: =-1*SUMIFS(Workings!$E:$E,Workings!$F:$F,'P&L'!$B9,Workings!$C:$C,'P&L'!D$3) -> -44 | E9: =-1*SUMIFS(Workings!$E:$E,Workings!$F:$F,'P&L'!$B9,Workings!$C:$C,'P&L'!E$3) -> -41
B10: EBIT | C10: =SUM(C8:C9) -> 277.82 | D10: =SUM(D8:D9) -> 311.66 | E10: =SUM(E8:E9) -> 563.76
B11: Interest expenses | C11: =-1*SUMIFS(Workings!$E:$E,Workings!$F:$F,'P&L'!$B11,Workings!$C:$C,'P&L'!C$3) -> -56 | D11: =-1*SUMIFS(Workings!$E:$E,Workings!$F:$F,'P&L'!$B11,Workings!$C:$C,'P&L'!D$3) -> -65 | E11: =-1*SUMIFS(Workings!$E:$E,Workings!$F:$F,'P&L'!$B11,Workings!$C:$C,'P&L'!E$3) -> -52
B12: EBT | C12: =SUM(C10:C11) -> 221.82 | D12: =SUM(D10:D11) -> 246.66 | E12: =SUM(E10:E11) -> 511.76
B13: Taxes | C13: =-1*SUMIFS(Workings!$E:$E,Workings!$F:$F,'P&L'!$B13,Workings!$C:$C,'P&L'!C$3) -> -207.52 | D13: =-1*SUMIFS(Workings!$E:$E,Workings!$F:$F,'P&L'!$B13,Workings!$C:$C,'P&L'!D$3) -> -209.98 | E13: =-1*SUMIFS(Workings!$E:$E,Workings!$F:$F,'P&L'!$B13,Workings!$C:$C,'P&L'!E$3) -> -208.58
B14: Net Income | C14: =SUM(C12:C13) -> 14.3 | D14: =SUM(D12:D13) -> 36.68 | E14: =SUM(E12:E13) -> 303.18
